axidence/__init__.py
axidence/context.py
axidence/dtypes.py
axidence/plugins/__init__.py
axidence/plugins/cuts/__init__.py
axidence/plugins/cuts/cut_isolated_s1.py
axidence/plugins/cuts/cut_isolated_s2.py
axidence/plugins/cuts/cut_pairing_exists.py
axidence/plugins/cuts/cuts_event_building.py
axidence/plugins/isolated/__init__.py
axidence/plugins/isolated/isolated_s1.py
axidence/plugins/isolated/isolated_s2.py
axidence/plugins/meta/__init__.py
axidence/plugins/meta/run_meta.py
axidence/plugins/pairing/__init__.py
axidence/plugins/pairing/events_paired.py
axidence/plugins/pairing/peaks_paired.py
axidence/plugins/salting/__init__.py
axidence/plugins/salting/event_building.py
axidence/plugins/salting/event_combine.py
axidence/plugins/salting/event_fields.py
axidence/plugins/salting/events_salting.py
axidence/plugins/salting/peak_correlation.py
axidence/plugins/salting/peaks_salted.py
axidence/samplers.py
axidence/utils.py
axidence-0.4.0.dist-info/LICENSE
axidence-0.4.0.dist-info/METADATA
axidence-0.4.0.dist-info/WHEEL
axidence-0.4.0.dist-info/RECORD
