Metadata-Version: 2.3
Name: axidence
Version: 0.4.0
Summary: strax-based data-driven accidental coincidence background simulation and peak-level salting
License: BSD-3-Clause
Author: Dacheng Xu,
Author-email: dx2227@columbia.edu
Requires-Python: >=3.10,<4.0
Classifier: Development Status :: 3 - Alpha
Classifier: Intended Audience :: Science/Research
Classifier: License :: OSI Approved :: BSD License
Classifier: Programming Language :: Python :: 3
Classifier: Programming Language :: Python :: 3.10
Classifier: Programming Language :: Python :: 3.11
Classifier: Programming Language :: Python :: 3.12
Classifier: Programming Language :: Python :: 3.13
Classifier: Programming Language :: Python :: 3 :: Only
Classifier: Topic :: Scientific/Engineering :: Physics
Requires-Dist: GOFevaluation (>=0.1.5)
Requires-Dist: strax (>=2.0.5)
Requires-Dist: straxen (>=3.2.0)
Project-URL: Documentation, https://readthedocs.org/projects/axidence/
Project-URL: Repository, https://github.com/XENONnT/axidence
